tuhlbox/__init__.py
tuhlbox/cli.py
tuhlbox/contributors.py
tuhlbox/doc2vec.py
tuhlbox/life.py
tuhlbox/stanza.py
tuhlbox/stringkernels.py
tuhlbox/subfreq.py
tuhlbox/torch_classifier.py
tuhlbox/torch_cnn.py
tuhlbox/torch_lstm.py
tuhlbox/transformernetworks.py
tuhlbox/tree.py
tuhlbox-0.4.15.dist-info/entry_points.txt
tuhlbox-0.4.15.dist-info/LICENSE
tuhlbox-0.4.15.dist-info/WHEEL
tuhlbox-0.4.15.dist-info/METADATA
tuhlbox-0.4.15.dist-info/RECORD
