Metadata-Version: 2.1
Name: tuhlbox
Version: 0.4.15
Summary: Personal toolbox of language processing models.
Home-page: https://git.uibk.ac.at/csak8736/tuhlbox
Author: Benjamin Murauer
Author-email: b.murauer@posteo.de
Requires-Python: >=3.7.0,<4.0.0
Classifier: Programming Language :: Python :: 3
Classifier: Programming Language :: Python :: 3.7
Classifier: Programming Language :: Python :: 3.8
Classifier: Programming Language :: Python :: 3.9
Requires-Dist: click (>=7.1.2,<8.0.0)
Requires-Dist: dstoolbox (>=0.10.1,<0.11.0)
Requires-Dist: gensim (>=4.0.1,<5.0.0)
Requires-Dist: langdetect (>=1.0.9,<2.0.0)
Requires-Dist: simpletransformers (>=0.51.1,<0.52.0)
Requires-Dist: sklearn (>=0.0,<0.1)
Requires-Dist: skorch (>=0.10.0,<0.11.0)
Requires-Dist: stanza (>=1.1.1,<2.0.0)
Requires-Dist: torch (>=1.7.0,<2.0.0)
Requires-Dist: treegrams (>=0.1.0,<0.2.0)
